{
    "name": "GlowLight",
    "size": {
        "width_cm": 16,
        "depth_cm": 16,
        "height_cm": 27,
        "preview_image": null
    },
    "weight_g": 1143,
    "ar_files": {
        "usdz": null
    },
    "finishes": [{
        "name": "Smooth White",
        "preview_image": null
    }, {
        "name": "Colorful Frost",
        "preview_image": null
    }],
    "LEDs": {
        "total": 60,
        "type": "WS2812B",
        "preview_image": null,
        "sections": [{
            "name": "Front left",
            "total": 15
        }, {
            "name": "Front right",
            "total": 15
        }, {
            "name": "Back left",
            "total": 15
        }, {
            "name": "Back right",
            "total": 15
        }],
        "brightness": {
            "max_value": 14,
            "max_unit": "watt",
            "max_scenario": "100% brightness, white",
            "preview_image": null
        },
        "colors": {
            "value": 16000000,
            "preview_image": null
        }
    },
    "control_options": {
        "wifi_internal": true,
        "actionbutton_internal": true,
        "powerbutton_internal": false,
        "wifi_preview_image": null,
        "actionbutton_preview_image": null,
        "powerbutton_preview_image": null
    },
    "power": {
        "supply": {
            "usbc_5v": true,
            "usbc_pd": false,
            "dc_connector": false,
            "usbc_preview_image": null,
            "dc_connector_preview_image": null
        },
        "consumption": {
            "watt_max": 15,
            "mA_max": 3000,
            "mA_LEDs_off": null,
            "limitable_in_software": true,
            "examples": [{
                "mode_name": null,
                "image": null,
                "mA_per_hour": null,
                "watt_per_hour": null
            }]
        }
    },
    "microcontroller": {
        "category": "ESP32",
        "version": "ESP32 WROOM 32E",
        "processor": {
            "cores": 2,
            "max_clock_mhz": 240,
            "languages": ["C", "MicroPython"]
        },
        "ulp_coprocessor": {
            "languages": ["assembly"]
        },
        "flash_MB": 4,
        "wifi": "802.11b/g/n",
        "bluetooth": "4.2 & LE"
    },
    "main_pcb": {
        "latest_pinout_pdf": "https://raw.githubusercontent.com/LEDs-by-glowingkitty/GlowTower/main/documents/pinout%20GlowLight%20GlowTower%20v1.0.pdf",
        "gpio_pins_accessible": [12, 13, 16, 25, 26, 33],
        "gpio_pins_features": ["RTC", "TOUCH", "ADC", "I2C"]
    },
    "firmware": {
        "name": "GlowOS",
        "latest_version": "0.15.1",
        "languages": ["EN"]
    },
    "usb_to_serial": "CP2102",
    "in_the_box": {
        "diy_kit": {
            "pcbs": [{
                "name": "Main PCB",
                "count": 1
            }, {
                "name": "Button PCB",
                "count": 1
            }, {
                "name": "GlowStripe PCB",
                "count": 4
            }],
            "case_parts": [{
                "name": "acrylic tube, 25cm tall",
                "count": 1
            }, {
                "name": "bottom case",
                "count": 1
            }, {
                "name": "bottom cover",
                "count": 1
            }, {
                "name": "top case",
                "count": 1
            }, {
                "name": "button",
                "count": 1
            }],
            "helper_parts": [{
                "name": "helper A",
                "count": 1
            }, {
                "name": "helper B",
                "count": 1
            }],
            "other_parts": [{
                "name": "screws & nuts"
            }, {
                "name": "solder"
            }]
        },
        "documents": ["Quick Start Guide"]
    }
}